example/__init__.py
example/main.py
extractor_wrapper/__init__.py
extractor_wrapper/base_extractor.py
extractor_wrapper/extractor_factory.py
extractor_wrapper/not_installed.py
extractor_wrapper/unsupported.py
extractor_wrapper/ext/__init__.py
extractor_wrapper/ext/doc.py
extractor_wrapper/ext/docx.py
extractor_wrapper/ext/msg.py
extractor_wrapper/ext/pdf.py
extractor_wrapper/ext/pptx.py
extractor_wrapper/ext/txt.py
extractor_wrapper/ext/xlsx.py
extractor_wrapper-0.1.2.dist-info/licenses/LICENSE
extractor_wrapper-0.1.2.dist-info/METADATA
extractor_wrapper-0.1.2.dist-info/WHEEL
extractor_wrapper-0.1.2.dist-info/top_level.txt
extractor_wrapper-0.1.2.dist-info/RECORD
