Metadata-Version: 2.4
Name: extractor_wrapper
Version: 0.1.2
Home-page: https://github.com/Florian-BARRE/ExtractorWrapper
Author: Florian BARRE
Author-email: florian.barre78@gmail.com
Classifier: Programming Language :: Python :: 3
Classifier: License :: OSI Approved :: GNU General Public License v3 (GPLv3)
Classifier: Operating System :: OS Independent
Requires-Python: >=3.10
License-File: LICENSE
Requires-Dist: beautifulsoup4
Requires-Dist: cffi
Requires-Dist: colorama
Requires-Dist: colorclass
Requires-Dist: compressed-rtf
Requires-Dist: contourpy
Requires-Dist: cryptography
Requires-Dist: cycler
Requires-Dist: easygui
Requires-Dist: ebcdic
Requires-Dist: et_xmlfile
Requires-Dist: extract-msg
Requires-Dist: fonttools
Requires-Dist: kiwisolver
Requires-Dist: lark
Requires-Dist: loggerplusplus
Requires-Dist: lxml
Requires-Dist: matplotlib
Requires-Dist: msoffcrypto-tool
Requires-Dist: numpy
Requires-Dist: olefile
Requires-Dist: oletools
Requires-Dist: openpyxl
Requires-Dist: packaging
Requires-Dist: pandas
Requires-Dist: pcodedmp
Requires-Dist: pillow
Requires-Dist: pycparser
Requires-Dist: pyparsing
Requires-Dist: PyPDF2
Requires-Dist: python-dateutil
Requires-Dist: python-docx
Requires-Dist: pytz
Requires-Dist: red-black-tree-mod
Requires-Dist: RTFDE
Requires-Dist: six
Requires-Dist: soupsieve
Requires-Dist: typing_extensions
Requires-Dist: tzdata
Requires-Dist: tzlocal
Requires-Dist: win_unicode_console
Dynamic: author
Dynamic: author-email
Dynamic: classifier
Dynamic: description
Dynamic: description-content-type
Dynamic: home-page
Dynamic: license-file
Dynamic: requires-dist
Dynamic: requires-python
